{"strm":"1242","semester":"Spring 2024","department":"ASL","updated_at":"2024-02-08T19:08:25.941507Z","courses":{"ASL::1020":{"subject":"ASL","subject_descr":"American Sign Language","catalog_number":"1020","descr":"Elementary American Sign Language II","topic":null,"units":"0","sessions":{"DRL::100":{"session_key":"DRL::100","class_nbr":null,"class_section":"100","section_type":"DRL","topic":null,"units":"0","instructors":[{"name":"Robert Strickler","email":"rls8ee@virginia.edu"}],"points":[{"timestamp":"2023-10-13T23:58:32.468791Z","enrollment_total":0,"class_capacity":18,"wait_tot":0,"wait_cap":199},{"timestamp":"2023-11-06T12:34:30.844263Z","enrollment_total":1,"class_capacity":18,"wait_tot":0,"wait_cap":199},{"timestamp":"2023-11-08T17:38:41.231889Z","enrollment_total":2,"class_capacity":18,"wait_tot":0,"wait_cap":199},{"timestamp":"2023-11-09T12:32:37.622063Z","enrollment_total":7,"class_capacity":18,"wait_tot":0,"wait_cap":199},{"timestamp":"2023-11-09T13:20:15.516539Z","enrollment_total":9,"class_capacity":18,"wait_tot":0,"wait_cap":199},{"timestamp":"2023-11-09T13:38:59.632553Z","enrollment_total":10,"class_capacity":18,"wait_tot":0,"wait_cap":199},{"timestamp":"2023-11-09T14:38:46.582349Z","enrollment_total":11,"class_capacity":18,"wait_tot":0,"wait_cap":199},{"timestamp":"2023-11-10T14:38:35.168074Z","enrollment_total":12,"class_capacity":18,"wait_tot":0,"wait_cap":199},{"timestamp":"2023-11-10T15:38:57.490982Z","enrollment_total":13,"class_capacity":18,"wait_tot":0,"wait_cap":199},{"timestamp":"2023-11-10T16:22:43.726035Z","enrollment_total":15,"class_capacity":18,"wait_tot":0,"wait_cap":199},{"timestamp":"2023-11-10T17:39:22.384638Z","enrollment_total":16,"class_capacity":18,"wait_tot":0,"wait_cap":199},{"timestamp":"2023-11-10T18:21:59.597024Z","enrollment_total":17,"class_capacity":18,"wait_tot":0,"wait_cap":199},{"timestamp":"2023-11-10T19:14:10.988833Z","enrollment_total":18,"class_capacity":18,"wait_tot":1,"wait_cap":199},{"timestamp":"2023-11-13T20:16:58.455632Z","enrollment_total":19,"class_capacity":18,"wait_tot":0,"wait_cap":199},{"timestamp":"2024-01-16T19:08:03.581926Z","enrollment_total":18,"class_capacity":18,"wait_tot":0,"wait_cap":199},{"timestamp":"2024-01-23T23:09:43.922102Z","enrollment_total":17,"class_capacity":18,"wait_tot":0,"wait_cap":199}]},"DRL::101":{"session_key":"DRL::101","class_nbr":null,"class_section":"101","section_type":"DRL","topic":null,"units":"0","instructors":[{"name":"Robert Strickler","email":"rls8ee@virginia.edu"}],"points":[{"timestamp":"2023-10-13T23:58:32.468791Z","enrollment_total":0,"class_capacity":18,"wait_tot":0,"wait_cap":199},{"timestamp":"2023-11-06T16:23:45.642424Z","enrollment_total":1,"class_capacity":18,"wait_tot":0,"wait_cap":199},{"timestamp":"2023-11-09T12:32:37.622063Z","enrollment_total":5,"class_capacity":18,"wait_tot":0,"wait_cap":199},{"timestamp":"2023-11-09T13:20:15.516539Z","enrollment_total":8,"class_capacity":18,"wait_tot":0,"wait_cap":199},{"timestamp":"2023-11-09T13:38:59.632553Z","enrollment_total":12,"class_capacity":18,"wait_tot":0,"wait_cap":199},{"timestamp":"2023-11-09T15:39:04.467391Z","enrollment_total":14,"class_capacity":18,"wait_tot":0,"wait_cap":199},{"timestamp":"2023-11-09T17:15:58.829155Z","enrollment_total":15,"class_capacity":18,"wait_tot":0,"wait_cap":199},{"timestamp":"2023-11-09T17:39:03.976511Z","enrollment_total":17,"class_capacity":18,"wait_tot":0,"wait_cap":199},{"timestamp":"2023-11-09T18:21:44.635477Z","enrollment_total":18,"class_capacity":18,"wait_tot":0,"wait_cap":199},{"timestamp":"2023-11-10T17:39:22.384638Z","enrollment_total":18,"class_capacity":18,"wait_tot":1,"wait_cap":199},{"timestamp":"2023-11-10T18:21:59.597024Z","enrollment_total":18,"class_capacity":18,"wait_tot":0,"wait_cap":199},{"timestamp":"2023-11-14T05:16:17.453252Z","enrollment_total":18,"class_capacity":18,"wait_tot":1,"wait_cap":199},{"timestamp":"2024-01-15T16:12:02.186444Z","enrollment_total":17,"class_capacity":18,"wait_tot":1,"wait_cap":199},{"timestamp":"2024-01-16T21:09:10.368708Z","enrollment_total":18,"class_capacity":18,"wait_tot":1,"wait_cap":199},{"timestamp":"2024-01-17T04:12:01.559255Z","enrollment_total":17,"class_capacity":18,"wait_tot":1,"wait_cap":199},{"timestamp":"2024-01-17T18:12:05.898383Z","enrollment_total":18,"class_capacity":18,"wait_tot":1,"wait_cap":199},{"timestamp":"2024-01-18T16:12:04.059128Z","enrollment_total":18,"class_capacity":18,"wait_tot":0,"wait_cap":199}]},"DRL::102":{"session_key":"DRL::102","class_nbr":null,"class_section":"102","section_type":"DRL","topic":null,"units":"0","instructors":[{"name":"-","email":""}],"points":[{"timestamp":"2023-10-13T23:58:32.468791Z","enrollment_total":0,"class_capacity":18,"wait_tot":0,"wait_cap":199},{"timestamp":"2023-11-06T12:34:30.844263Z","enrollment_total":1,"class_capacity":18,"wait_tot":0,"wait_cap":199},{"timestamp":"2023-11-08T12:39:21.465681Z","enrollment_total":2,"class_capacity":18,"wait_tot":0,"wait_cap":199},{"timestamp":"2023-11-08T19:14:09.876621Z","enrollment_total":3,"class_capacity":18,"wait_tot":0,"wait_cap":199},{"timestamp":"2023-11-09T12:32:37.622063Z","enrollment_total":6,"class_capacity":18,"wait_tot":0,"wait_cap":199},{"timestamp":"2023-11-09T14:38:46.582349Z","enrollment_total":7,"class_capacity":18,"wait_tot":0,"wait_cap":199},{"timestamp":"2023-11-09T15:17:59.086709Z","enrollment_total":6,"class_capacity":18,"wait_tot":0,"wait_cap":199},{"timestamp":"2023-11-09T16:22:48.633140Z","enrollment_total":7,"class_capacity":18,"wait_tot":0,"wait_cap":199},{"timestamp":"2023-11-09T19:14:03.128774Z","enrollment_total":8,"class_capacity":18,"wait_tot":1,"wait_cap":199},{"timestamp":"2023-11-10T14:38:35.168074Z","enrollment_total":10,"class_capacity":18,"wait_tot":1,"wait_cap":199},{"timestamp":"2023-11-10T15:38:57.490982Z","enrollment_total":11,"class_capacity":18,"wait_tot":1,"wait_cap":199},{"timestamp":"2023-11-10T16:22:43.726035Z","enrollment_total":12,"class_capacity":18,"wait_tot":1,"wait_cap":199},{"timestamp":"2023-11-10T16:42:01.972637Z","enrollment_total":13,"class_capacity":18,"wait_tot":1,"wait_cap":199},{"timestamp":"2023-11-10T17:15:48.697229Z","enrollment_total":16,"class_capacity":18,"wait_tot":1,"wait_cap":199},{"timestamp":"2023-11-10T18:21:59.597024Z","enrollment_total":17,"class_capacity":18,"wait_tot":1,"wait_cap":199},{"timestamp":"2023-11-10T19:14:10.988833Z","enrollment_total":18,"class_capacity":18,"wait_tot":2,"wait_cap":199},{"timestamp":"2023-11-28T06:13:21.378284Z","enrollment_total":17,"class_capacity":18,"wait_tot":2,"wait_cap":199},{"timestamp":"2023-11-28T10:10:31.484323Z","enrollment_total":18,"class_capacity":18,"wait_tot":1,"wait_cap":199},{"timestamp":"2023-12-28T06:12:28.172757Z","enrollment_total":17,"class_capacity":18,"wait_tot":1,"wait_cap":199},{"timestamp":"2023-12-28T20:09:24.417323Z","enrollment_total":18,"class_capacity":18,"wait_tot":1,"wait_cap":199},{"timestamp":"2024-01-10T06:12:58.879342Z","enrollment_total":18,"class_capacity":18,"wait_tot":0,"wait_cap":199},{"timestamp":"2024-01-16T21:09:10.368708Z","enrollment_total":17,"class_capacity":18,"wait_tot":0,"wait_cap":199},{"timestamp":"2024-01-16T23:09:29.897101Z","enrollment_total":18,"class_capacity":18,"wait_tot":0,"wait_cap":199}]},"DRL::103":{"session_key":"DRL::103","class_nbr":null,"class_section":"103","section_type":"DRL","topic":null,"units":"0","instructors":[{"name":"Amy Ashworth","email":"xsx3jr@virginia.edu"}],"points":[{"timestamp":"2023-10-13T23:58:32.468791Z","enrollment_total":0,"class_capacity":18,"wait_tot":0,"wait_cap":199},{"timestamp":"2023-11-06T12:34:30.844263Z","enrollment_total":1,"class_capacity":18,"wait_tot":0,"wait_cap":199},{"timestamp":"2023-11-08T20:18:06.581396Z","enrollment_total":2,"class_capacity":18,"wait_tot":0,"wait_cap":199},{"timestamp":"2023-11-09T13:20:15.516539Z","enrollment_total":3,"class_capacity":18,"wait_tot":0,"wait_cap":199},{"timestamp":"2023-11-09T15:17:59.086709Z","enrollment_total":4,"class_capacity":18,"wait_tot":0,"wait_cap":199},{"timestamp":"2023-11-09T17:15:58.829155Z","enrollment_total":6,"class_capacity":18,"wait_tot":0,"wait_cap":199},{"timestamp":"2023-11-10T19:14:10.988833Z","enrollment_total":8,"class_capacity":18,"wait_tot":0,"wait_cap":199},{"timestamp":"2023-11-10T21:14:44.726634Z","enrollment_total":9,"class_capacity":18,"wait_tot":0,"wait_cap":199},{"timestamp":"2023-11-10T22:15:54.775719Z","enrollment_total":10,"class_capacity":18,"wait_tot":0,"wait_cap":199},{"timestamp":"2023-11-29T05:09:23.511289Z","enrollment_total":11,"class_capacity":18,"wait_tot":0,"wait_cap":199},{"timestamp":"2023-12-25T00:41:25.514020Z","enrollment_total":10,"class_capacity":18,"wait_tot":0,"wait_cap":199},{"timestamp":"2023-12-28T06:12:28.172757Z","enrollment_total":11,"class_capacity":18,"wait_tot":0,"wait_cap":199},{"timestamp":"2023-12-28T20:09:24.417323Z","enrollment_total":10,"class_capacity":18,"wait_tot":0,"wait_cap":199},{"timestamp":"2024-01-08T23:09:56.563852Z","enrollment_total":9,"class_capacity":18,"wait_tot":0,"wait_cap":199},{"timestamp":"2024-01-10T06:12:58.879342Z","enrollment_total":10,"class_capacity":18,"wait_tot":0,"wait_cap":199},{"timestamp":"2024-01-16T23:09:29.897101Z","enrollment_total":9,"class_capacity":18,"wait_tot":0,"wait_cap":199}]},"SEM::001":{"session_key":"SEM::001","class_nbr":null,"class_section":"001","section_type":"SEM","topic":null,"units":"4","instructors":[{"name":"Gregory Propp","email":"gp5c@virginia.edu"}],"points":[{"timestamp":"2023-10-13T23:58:32.468791Z","enrollment_total":0,"class_capacity":18,"wait_tot":0,"wait_cap":199},{"timestamp":"2023-11-06T12:34:30.844263Z","enrollment_total":1,"class_capacity":18,"wait_tot":0,"wait_cap":199},{"timestamp":"2023-11-09T14:38:46.582349Z","enrollment_total":2,"class_capacity":18,"wait_tot":0,"wait_cap":199},{"timestamp":"2023-11-09T17:15:58.829155Z","enrollment_total":3,"class_capacity":18,"wait_tot":0,"wait_cap":199},{"timestamp":"2023-11-09T17:39:03.976511Z","enrollment_total":5,"class_capacity":18,"wait_tot":0,"wait_cap":199},{"timestamp":"2023-11-10T14:38:35.168074Z","enrollment_total":6,"class_capacity":18,"wait_tot":0,"wait_cap":199},{"timestamp":"2023-11-10T15:38:57.490982Z","enrollment_total":8,"class_capacity":18,"wait_tot":0,"wait_cap":199},{"timestamp":"2023-11-10T17:15:48.697229Z","enrollment_total":11,"class_capacity":18,"wait_tot":0,"wait_cap":199},{"timestamp":"2023-11-10T17:39:22.384638Z","enrollment_total":12,"class_capacity":18,"wait_tot":0,"wait_cap":199},{"timestamp":"2023-11-10T18:21:59.597024Z","enrollment_total":13,"class_capacity":18,"wait_tot":0,"wait_cap":199},{"timestamp":"2023-11-10T19:14:10.988833Z","enrollment_total":17,"class_capacity":18,"wait_tot":1,"wait_cap":199},{"timestamp":"2023-11-10T22:15:54.775719Z","enrollment_total":18,"class_capacity":18,"wait_tot":1,"wait_cap":199},{"timestamp":"2023-11-13T20:16:58.455632Z","enrollment_total":18,"class_capacity":18,"wait_tot":0,"wait_cap":199},{"timestamp":"2023-12-28T06:12:28.172757Z","enrollment_total":17,"class_capacity":18,"wait_tot":0,"wait_cap":199},{"timestamp":"2024-01-08T23:09:56.563852Z","enrollment_total":16,"class_capacity":18,"wait_tot":1,"wait_cap":199},{"timestamp":"2024-01-10T06:12:58.879342Z","enrollment_total":17,"class_capacity":18,"wait_tot":0,"wait_cap":199},{"timestamp":"2024-01-16T04:11:49.821497Z","enrollment_total":18,"class_capacity":18,"wait_tot":0,"wait_cap":199},{"timestamp":"2024-01-23T19:07:57.584632Z","enrollment_total":17,"class_capacity":18,"wait_tot":0,"wait_cap":199}]},"SEM::002":{"session_key":"SEM::002","class_nbr":null,"class_section":"002","section_type":"SEM","topic":null,"units":"4","instructors":[{"name":"Rocco Devito","email":"rjd4h@virginia.edu"}],"points":[{"timestamp":"2023-10-13T23:58:32.468791Z","enrollment_total":0,"class_capacity":18,"wait_tot":0,"wait_cap":199},{"timestamp":"2023-11-06T12:34:30.844263Z","enrollment_total":1,"class_capacity":18,"wait_tot":0,"wait_cap":199},{"timestamp":"2023-11-09T12:32:37.622063Z","enrollment_total":6,"class_capacity":18,"wait_tot":0,"wait_cap":199},{"timestamp":"2023-11-09T13:20:15.516539Z","enrollment_total":10,"class_capacity":18,"wait_tot":0,"wait_cap":199},{"timestamp":"2023-11-09T13:38:59.632553Z","enrollment_total":11,"class_capacity":18,"wait_tot":0,"wait_cap":199},{"timestamp":"2023-11-09T14:38:46.582349Z","enrollment_total":12,"class_capacity":18,"wait_tot":0,"wait_cap":199},{"timestamp":"2023-11-09T15:39:04.467391Z","enrollment_total":13,"class_capacity":18,"wait_tot":0,"wait_cap":199},{"timestamp":"2023-11-09T17:15:58.829155Z","enrollment_total":15,"class_capacity":18,"wait_tot":0,"wait_cap":199},{"timestamp":"2023-11-09T19:14:03.128774Z","enrollment_total":16,"class_capacity":18,"wait_tot":0,"wait_cap":199},{"timestamp":"2023-11-10T14:38:35.168074Z","enrollment_total":18,"class_capacity":18,"wait_tot":0,"wait_cap":199},{"timestamp":"2023-11-10T17:15:48.697229Z","enrollment_total":18,"class_capacity":18,"wait_tot":1,"wait_cap":199},{"timestamp":"2023-11-10T17:39:22.384638Z","enrollment_total":18,"class_capacity":18,"wait_tot":2,"wait_cap":199},{"timestamp":"2023-11-14T05:16:17.453252Z","enrollment_total":18,"class_capacity":18,"wait_tot":1,"wait_cap":199},{"timestamp":"2023-12-03T06:11:32.864999Z","enrollment_total":18,"class_capacity":18,"wait_tot":2,"wait_cap":199},{"timestamp":"2023-12-25T00:41:25.514020Z","enrollment_total":17,"class_capacity":18,"wait_tot":2,"wait_cap":199},{"timestamp":"2023-12-28T06:12:28.172757Z","enrollment_total":18,"class_capacity":18,"wait_tot":1,"wait_cap":199},{"timestamp":"2024-01-08T23:09:56.563852Z","enrollment_total":18,"class_capacity":18,"wait_tot":0,"wait_cap":199},{"timestamp":"2024-01-15T16:12:02.186444Z","enrollment_total":17,"class_capacity":18,"wait_tot":0,"wait_cap":199},{"timestamp":"2024-01-21T23:09:34.256965Z","enrollment_total":16,"class_capacity":18,"wait_tot":0,"wait_cap":199},{"timestamp":"2024-01-23T19:07:57.584632Z","enrollment_total":17,"class_capacity":18,"wait_tot":0,"wait_cap":199},{"timestamp":"2024-01-23T23:09:43.922102Z","enrollment_total":16,"class_capacity":18,"wait_tot":0,"wait_cap":199}]},"SEM::003":{"session_key":"SEM::003","class_nbr":null,"class_section":"003","section_type":"SEM","topic":null,"units":"4","instructors":[{"name":"Rocco Devito","email":"rjd4h@virginia.edu"}],"points":[{"timestamp":"2023-10-13T23:58:32.468791Z","enrollment_total":0,"class_capacity":18,"wait_tot":0,"wait_cap":199},{"timestamp":"2023-11-06T12:34:30.844263Z","enrollment_total":1,"class_capacity":18,"wait_tot":0,"wait_cap":199},{"timestamp":"2023-11-06T16:23:45.642424Z","enrollment_total":2,"class_capacity":18,"wait_tot":0,"wait_cap":199},{"timestamp":"2023-11-08T12:39:21.465681Z","enrollment_total":3,"class_capacity":18,"wait_tot":0,"wait_cap":199},{"timestamp":"2023-11-08T17:38:41.231889Z","enrollment_total":4,"class_capacity":18,"wait_tot":0,"wait_cap":199},{"timestamp":"2023-11-08T20:18:06.581396Z","enrollment_total":5,"class_capacity":18,"wait_tot":0,"wait_cap":199},{"timestamp":"2023-11-09T12:32:37.622063Z","enrollment_total":12,"class_capacity":18,"wait_tot":0,"wait_cap":199},{"timestamp":"2023-11-09T13:20:15.516539Z","enrollment_total":14,"class_capacity":18,"wait_tot":0,"wait_cap":199},{"timestamp":"2023-11-09T13:38:59.632553Z","enrollment_total":18,"class_capacity":18,"wait_tot":0,"wait_cap":199},{"timestamp":"2023-11-09T19:14:03.128774Z","enrollment_total":18,"class_capacity":18,"wait_tot":1,"wait_cap":199},{"timestamp":"2023-11-10T17:15:48.697229Z","enrollment_total":18,"class_capacity":18,"wait_tot":2,"wait_cap":199},{"timestamp":"2023-11-10T19:14:10.988833Z","enrollment_total":18,"class_capacity":18,"wait_tot":3,"wait_cap":199},{"timestamp":"2023-11-14T05:16:17.453252Z","enrollment_total":18,"class_capacity":18,"wait_tot":4,"wait_cap":199},{"timestamp":"2023-11-14T23:17:40.561371Z","enrollment_total":18,"class_capacity":18,"wait_tot":3,"wait_cap":199},{"timestamp":"2023-11-28T06:13:21.378284Z","enrollment_total":17,"class_capacity":18,"wait_tot":3,"wait_cap":199},{"timestamp":"2023-11-28T10:10:31.484323Z","enrollment_total":18,"class_capacity":18,"wait_tot":2,"wait_cap":199},{"timestamp":"2024-01-08T23:09:56.563852Z","enrollment_total":18,"class_capacity":18,"wait_tot":1,"wait_cap":199},{"timestamp":"2024-01-16T04:11:49.821497Z","enrollment_total":17,"class_capacity":18,"wait_tot":1,"wait_cap":199},{"timestamp":"2024-01-16T19:08:03.581926Z","enrollment_total":16,"class_capacity":18,"wait_tot":1,"wait_cap":199},{"timestamp":"2024-01-17T04:12:01.559255Z","enrollment_total":15,"class_capacity":18,"wait_tot":1,"wait_cap":199},{"timestamp":"2024-01-17T18:12:05.898383Z","enrollment_total":16,"class_capacity":18,"wait_tot":1,"wait_cap":199},{"timestamp":"2024-01-18T16:12:04.059128Z","enrollment_total":17,"class_capacity":18,"wait_tot":0,"wait_cap":199},{"timestamp":"2024-01-21T23:09:34.256965Z","enrollment_total":18,"class_capacity":18,"wait_tot":0,"wait_cap":199}]},"SEM::004":{"session_key":"SEM::004","class_nbr":null,"class_section":"004","section_type":"SEM","topic":null,"units":"4","instructors":[{"name":"Maher Eshgi","email":"zdr4rs@virginia.edu"}],"points":[{"timestamp":"2023-10-13T23:58:32.468791Z","enrollment_total":0,"class_capacity":18,"wait_tot":0,"wait_cap":199},{"timestamp":"2023-11-08T19:14:09.876621Z","enrollment_total":1,"class_capacity":18,"wait_tot":0,"wait_cap":199},{"timestamp":"2023-11-09T15:39:04.467391Z","enrollment_total":2,"class_capacity":18,"wait_tot":0,"wait_cap":199},{"timestamp":"2023-11-09T16:22:48.633140Z","enrollment_total":3,"class_capacity":18,"wait_tot":0,"wait_cap":199},{"timestamp":"2023-11-09T18:21:44.635477Z","enrollment_total":4,"class_capacity":18,"wait_tot":0,"wait_cap":199},{"timestamp":"2023-11-10T16:22:43.726035Z","enrollment_total":7,"class_capacity":18,"wait_tot":0,"wait_cap":199},{"timestamp":"2023-11-10T16:42:01.972637Z","enrollment_total":8,"class_capacity":18,"wait_tot":0,"wait_cap":199},{"timestamp":"2023-11-10T18:21:59.597024Z","enrollment_total":9,"class_capacity":18,"wait_tot":0,"wait_cap":199},{"timestamp":"2023-11-10T21:14:44.726634Z","enrollment_total":10,"class_capacity":18,"wait_tot":0,"wait_cap":199},{"timestamp":"2023-11-13T20:16:58.455632Z","enrollment_total":11,"class_capacity":18,"wait_tot":0,"wait_cap":199},{"timestamp":"2023-11-29T05:09:23.511289Z","enrollment_total":12,"class_capacity":18,"wait_tot":0,"wait_cap":199},{"timestamp":"2024-01-18T16:12:04.059128Z","enrollment_total":11,"class_capacity":18,"wait_tot":0,"wait_cap":199}]}}},"ASL::2020":{"subject":"ASL","subject_descr":"American Sign Language","catalog_number":"2020","descr":"Intermediate American Sign Language II","topic":null,"units":"3","sessions":{"SEM::001":{"session_key":"SEM::001","class_nbr":null,"class_section":"001","section_type":"SEM","topic":null,"units":"3","instructors":[{"name":"Maher Eshgi","email":"zdr4rs@virginia.edu"}],"points":[{"timestamp":"2023-10-13T23:58:32.468791Z","enrollment_total":0,"class_capacity":16,"wait_tot":0,"wait_cap":199},{"timestamp":"2023-11-06T18:22:35.405561Z","enrollment_total":1,"class_capacity":16,"wait_tot":0,"wait_cap":199},{"timestamp":"2023-11-06T19:38:37.466607Z","enrollment_total":2,"class_capacity":16,"wait_tot":0,"wait_cap":199},{"timestamp":"2023-11-08T17:15:53.869560Z","enrollment_total":3,"class_capacity":16,"wait_tot":0,"wait_cap":199},{"timestamp":"2023-11-08T19:14:09.876621Z","enrollment_total":4,"class_capacity":16,"wait_tot":0,"wait_cap":199},{"timestamp":"2023-11-08T19:38:42.241253Z","enrollment_total":5,"class_capacity":16,"wait_tot":0,"wait_cap":199},{"timestamp":"2023-11-09T16:22:48.633140Z","enrollment_total":6,"class_capacity":16,"wait_tot":0,"wait_cap":199},{"timestamp":"2023-11-09T17:15:58.829155Z","enrollment_total":9,"class_capacity":16,"wait_tot":0,"wait_cap":199},{"timestamp":"2023-11-09T19:14:03.128774Z","enrollment_total":10,"class_capacity":16,"wait_tot":0,"wait_cap":199},{"timestamp":"2023-11-12T16:20:05.491571Z","enrollment_total":9,"class_capacity":16,"wait_tot":0,"wait_cap":199},{"timestamp":"2024-01-05T00:41:09.760043Z","enrollment_total":10,"class_capacity":16,"wait_tot":0,"wait_cap":199},{"timestamp":"2024-01-15T03:10:42.677070Z","enrollment_total":9,"class_capacity":16,"wait_tot":0,"wait_cap":199}]},"SEM::002":{"session_key":"SEM::002","class_nbr":null,"class_section":"002","section_type":"SEM","topic":null,"units":"3","instructors":[{"name":"Maher Eshgi","email":"zdr4rs@virginia.edu"}],"points":[{"timestamp":"2023-10-13T23:58:32.468791Z","enrollment_total":0,"class_capacity":16,"wait_tot":0,"wait_cap":199},{"timestamp":"2023-11-06T15:19:29.887357Z","enrollment_total":1,"class_capacity":16,"wait_tot":0,"wait_cap":199},{"timestamp":"2023-11-06T18:39:39.259055Z","enrollment_total":2,"class_capacity":16,"wait_tot":0,"wait_cap":199},{"timestamp":"2023-11-08T12:39:21.465681Z","enrollment_total":3,"class_capacity":16,"wait_tot":0,"wait_cap":199},{"timestamp":"2023-11-08T14:38:58.297561Z","enrollment_total":4,"class_capacity":16,"wait_tot":0,"wait_cap":199},{"timestamp":"2023-11-08T15:18:28.477350Z","enrollment_total":5,"class_capacity":16,"wait_tot":0,"wait_cap":199},{"timestamp":"2023-11-08T19:14:09.876621Z","enrollment_total":4,"class_capacity":16,"wait_tot":0,"wait_cap":199},{"timestamp":"2023-11-08T20:18:06.581396Z","enrollment_total":5,"class_capacity":16,"wait_tot":0,"wait_cap":199},{"timestamp":"2023-11-09T15:17:59.086709Z","enrollment_total":6,"class_capacity":16,"wait_tot":0,"wait_cap":199},{"timestamp":"2023-11-09T15:39:04.467391Z","enrollment_total":7,"class_capacity":16,"wait_tot":0,"wait_cap":199},{"timestamp":"2023-11-09T16:22:48.633140Z","enrollment_total":9,"class_capacity":16,"wait_tot":0,"wait_cap":199},{"timestamp":"2023-11-09T16:42:09.019908Z","enrollment_total":10,"class_capacity":16,"wait_tot":0,"wait_cap":199},{"timestamp":"2023-11-09T18:21:44.635477Z","enrollment_total":12,"class_capacity":16,"wait_tot":0,"wait_cap":199},{"timestamp":"2023-11-09T18:39:12.697407Z","enrollment_total":13,"class_capacity":16,"wait_tot":0,"wait_cap":199},{"timestamp":"2023-11-09T19:14:03.128774Z","enrollment_total":14,"class_capacity":16,"wait_tot":0,"wait_cap":199},{"timestamp":"2023-11-10T02:39:51.272149Z","enrollment_total":15,"class_capacity":16,"wait_tot":0,"wait_cap":199},{"timestamp":"2023-11-10T22:15:54.775719Z","enrollment_total":14,"class_capacity":16,"wait_tot":0,"wait_cap":199},{"timestamp":"2023-11-12T19:38:28.214871Z","enrollment_total":15,"class_capacity":16,"wait_tot":0,"wait_cap":199},{"timestamp":"2023-11-27T14:09:24.679721Z","enrollment_total":16,"class_capacity":16,"wait_tot":0,"wait_cap":199},{"timestamp":"2024-01-12T22:09:09.811062Z","enrollment_total":16,"class_capacity":16,"wait_tot":1,"wait_cap":199},{"timestamp":"2024-01-15T20:10:07.240255Z","enrollment_total":16,"class_capacity":16,"wait_tot":0,"wait_cap":199}]},"SEM::003":{"session_key":"SEM::003","class_nbr":null,"class_section":"003","section_type":"SEM","topic":null,"units":"3","instructors":[{"name":"Gregory Propp","email":"gp5c@virginia.edu"}],"points":[{"timestamp":"2023-10-13T23:58:32.468791Z","enrollment_total":0,"class_capacity":16,"wait_tot":0,"wait_cap":199},{"timestamp":"2023-11-06T14:17:03.409400Z","enrollment_total":1,"class_capacity":16,"wait_tot":0,"wait_cap":199},{"timestamp":"2023-11-06T14:39:36.393616Z","enrollment_total":2,"class_capacity":16,"wait_tot":0,"wait_cap":199},{"timestamp":"2023-11-06T15:19:29.887357Z","enrollment_total":1,"class_capacity":16,"wait_tot":0,"wait_cap":199},{"timestamp":"2023-11-06T18:22:35.405561Z","enrollment_total":2,"class_capacity":16,"wait_tot":0,"wait_cap":199},{"timestamp":"2023-11-08T12:39:21.465681Z","enrollment_total":4,"class_capacity":16,"wait_tot":0,"wait_cap":199},{"timestamp":"2023-11-08T16:23:04.539371Z","enrollment_total":5,"class_capacity":16,"wait_tot":0,"wait_cap":199},{"timestamp":"2023-11-08T17:15:53.869560Z","enrollment_total":8,"class_capacity":16,"wait_tot":0,"wait_cap":199},{"timestamp":"2023-11-08T17:38:41.231889Z","enrollment_total":10,"class_capacity":16,"wait_tot":0,"wait_cap":199},{"timestamp":"2023-11-08T19:38:42.241253Z","enrollment_total":13,"class_capacity":16,"wait_tot":0,"wait_cap":199},{"timestamp":"2023-11-09T12:32:37.622063Z","enrollment_total":15,"class_capacity":16,"wait_tot":0,"wait_cap":199},{"timestamp":"2023-11-09T13:20:15.516539Z","enrollment_total":16,"class_capacity":16,"wait_tot":0,"wait_cap":199},{"timestamp":"2023-11-09T14:38:46.582349Z","enrollment_total":16,"class_capacity":16,"wait_tot":2,"wait_cap":199},{"timestamp":"2023-11-09T15:39:04.467391Z","enrollment_total":16,"class_capacity":16,"wait_tot":3,"wait_cap":199},{"timestamp":"2023-11-09T16:22:48.633140Z","enrollment_total":16,"class_capacity":16,"wait_tot":4,"wait_cap":199},{"timestamp":"2023-11-09T17:39:03.976511Z","enrollment_total":16,"class_capacity":16,"wait_tot":5,"wait_cap":199},{"timestamp":"2023-11-09T19:14:03.128774Z","enrollment_total":16,"class_capacity":16,"wait_tot":7,"wait_cap":199},{"timestamp":"2023-11-10T02:39:51.272149Z","enrollment_total":16,"class_capacity":16,"wait_tot":8,"wait_cap":199},{"timestamp":"2023-11-11T02:41:28.108521Z","enrollment_total":16,"class_capacity":16,"wait_tot":9,"wait_cap":199},{"timestamp":"2023-11-12T19:38:28.214871Z","enrollment_total":16,"class_capacity":16,"wait_tot":8,"wait_cap":199},{"timestamp":"2023-11-27T14:09:24.679721Z","enrollment_total":16,"class_capacity":16,"wait_tot":7,"wait_cap":199},{"timestamp":"2024-01-05T02:23:35.006444Z","enrollment_total":16,"class_capacity":16,"wait_tot":8,"wait_cap":199},{"timestamp":"2024-01-10T17:09:15.746896Z","enrollment_total":16,"class_capacity":16,"wait_tot":7,"wait_cap":199},{"timestamp":"2024-01-15T03:10:42.677070Z","enrollment_total":16,"class_capacity":16,"wait_tot":6,"wait_cap":199},{"timestamp":"2024-01-17T19:08:02.813108Z","enrollment_total":16,"class_capacity":16,"wait_tot":5,"wait_cap":199},{"timestamp":"2024-01-17T22:09:27.450775Z","enrollment_total":16,"class_capacity":16,"wait_tot":4,"wait_cap":199},{"timestamp":"2024-01-18T19:08:16.693797Z","enrollment_total":16,"class_capacity":16,"wait_tot":3,"wait_cap":199},{"timestamp":"2024-01-30T01:42:01.120734Z","enrollment_total":17,"class_capacity":16,"wait_tot":2,"wait_cap":199},{"timestamp":"2024-01-30T18:11:36.693018Z","enrollment_total":18,"class_capacity":16,"wait_tot":1,"wait_cap":199},{"timestamp":"2024-01-30T19:07:44.435927Z","enrollment_total":19,"class_capacity":16,"wait_tot":0,"wait_cap":199}]},"SEM::004":{"session_key":"SEM::004","class_nbr":null,"class_section":"004","section_type":"SEM","topic":null,"units":"3","instructors":[{"name":"Gregory Propp","email":"gp5c@virginia.edu"}],"points":[{"timestamp":"2023-10-13T23:58:32.468791Z","enrollment_total":0,"class_capacity":16,"wait_tot":0,"wait_cap":199},{"timestamp":"2023-11-06T15:19:29.887357Z","enrollment_total":2,"class_capacity":16,"wait_tot":0,"wait_cap":199},{"timestamp":"2023-11-06T15:38:54.860895Z","enrollment_total":3,"class_capacity":16,"wait_tot":0,"wait_cap":199},{"timestamp":"2023-11-06T17:38:48.570786Z","enrollment_total":4,"class_capacity":16,"wait_tot":0,"wait_cap":199},{"timestamp":"2023-11-06T18:22:35.405561Z","enrollment_total":5,"class_capacity":16,"wait_tot":0,"wait_cap":199},{"timestamp":"2023-11-06T19:38:37.466607Z","enrollment_total":6,"class_capacity":16,"wait_tot":0,"wait_cap":199},{"timestamp":"2023-11-08T12:39:21.465681Z","enrollment_total":9,"class_capacity":16,"wait_tot":0,"wait_cap":199},{"timestamp":"2023-11-08T15:18:28.477350Z","enrollment_total":10,"class_capacity":16,"wait_tot":0,"wait_cap":199},{"timestamp":"2023-11-08T17:38:41.231889Z","enrollment_total":11,"class_capacity":16,"wait_tot":0,"wait_cap":199},{"timestamp":"2023-11-08T18:39:29.892410Z","enrollment_total":13,"class_capacity":16,"wait_tot":0,"wait_cap":199},{"timestamp":"2023-11-09T12:32:37.622063Z","enrollment_total":14,"class_capacity":16,"wait_tot":0,"wait_cap":199},{"timestamp":"2023-11-09T13:20:15.516539Z","enrollment_total":16,"class_capacity":16,"wait_tot":2,"wait_cap":199},{"timestamp":"2023-11-09T14:38:46.582349Z","enrollment_total":16,"class_capacity":16,"wait_tot":3,"wait_cap":199},{"timestamp":"2023-11-09T17:15:58.829155Z","enrollment_total":16,"class_capacity":16,"wait_tot":5,"wait_cap":199},{"timestamp":"2023-11-09T18:21:44.635477Z","enrollment_total":16,"class_capacity":16,"wait_tot":7,"wait_cap":199},{"timestamp":"2023-11-09T19:14:03.128774Z","enrollment_total":16,"class_capacity":16,"wait_tot":9,"wait_cap":199},{"timestamp":"2023-11-11T02:41:28.108521Z","enrollment_total":16,"class_capacity":16,"wait_tot":10,"wait_cap":199},{"timestamp":"2023-11-13T16:22:51.328192Z","enrollment_total":18,"class_capacity":16,"wait_tot":8,"wait_cap":199},{"timestamp":"2023-11-27T14:09:24.679721Z","enrollment_total":18,"class_capacity":16,"wait_tot":7,"wait_cap":199},{"timestamp":"2023-11-27T15:10:09.536984Z","enrollment_total":18,"class_capacity":16,"wait_tot":8,"wait_cap":199},{"timestamp":"2024-01-16T19:08:03.581926Z","enrollment_total":18,"class_capacity":16,"wait_tot":7,"wait_cap":199},{"timestamp":"2024-01-17T19:08:02.813108Z","enrollment_total":18,"class_capacity":16,"wait_tot":6,"wait_cap":199},{"timestamp":"2024-01-30T00:39:02.256431Z","enrollment_total":19,"class_capacity":16,"wait_tot":5,"wait_cap":199},{"timestamp":"2024-01-30T02:15:33.144461Z","enrollment_total":20,"class_capacity":16,"wait_tot":4,"wait_cap":199},{"timestamp":"2024-01-30T04:10:41.657307Z","enrollment_total":21,"class_capacity":16,"wait_tot":3,"wait_cap":199},{"timestamp":"2024-01-30T18:11:36.693018Z","enrollment_total":22,"class_capacity":16,"wait_tot":2,"wait_cap":199},{"timestamp":"2024-01-31T00:39:16.980396Z","enrollment_total":22,"class_capacity":16,"wait_tot":1,"wait_cap":199},{"timestamp":"2024-02-08T19:08:25.941507Z","enrollment_total":22,"class_capacity":16,"wait_tot":0,"wait_cap":199}]}}},"ASL::3015":{"subject":"ASL","subject_descr":"American Sign Language","catalog_number":"3015","descr":"Language House Conversation in ASL","topic":null,"units":"1","sessions":{"PRA::001":{"session_key":"PRA::001","class_nbr":null,"class_section":"001","section_type":"PRA","topic":null,"units":"1","instructors":[{"name":"Gregory Propp","email":"gp5c@virginia.edu"}],"points":[{"timestamp":"2023-10-13T23:58:32.468791Z","enrollment_total":0,"class_capacity":12,"wait_tot":0,"wait_cap":0},{"timestamp":"2024-01-20T03:10:20.137462Z","enrollment_total":1,"class_capacity":12,"wait_tot":0,"wait_cap":0},{"timestamp":"2024-01-23T01:55:19.288389Z","enrollment_total":2,"class_capacity":12,"wait_tot":0,"wait_cap":0},{"timestamp":"2024-01-23T03:10:41.270839Z","enrollment_total":3,"class_capacity":12,"wait_tot":0,"wait_cap":0},{"timestamp":"2024-01-24T19:08:42.213416Z","enrollment_total":4,"class_capacity":12,"wait_tot":0,"wait_cap":0},{"timestamp":"2024-01-30T21:09:13.541491Z","enrollment_total":5,"class_capacity":12,"wait_tot":0,"wait_cap":0},{"timestamp":"2024-01-31T01:42:28.263995Z","enrollment_total":6,"class_capacity":12,"wait_tot":0,"wait_cap":0},{"timestamp":"2024-01-31T16:11:05.423976Z","enrollment_total":7,"class_capacity":12,"wait_tot":0,"wait_cap":0},{"timestamp":"2024-01-31T20:09:28.278479Z","enrollment_total":8,"class_capacity":12,"wait_tot":0,"wait_cap":0}]}}},"ASL::3559":{"subject":"ASL","subject_descr":"American Sign Language","catalog_number":"3559","descr":"New Course in American Sign Language","topic":"Extended Narratives in ASL","units":"3","sessions":{"Lecture::001":{"session_key":"Lecture::001","class_nbr":null,"class_section":"001","section_type":"Lecture","topic":"Extended Narratives in ASL","units":"3","instructors":[{"name":"Bruce Sofinski","email":"bs3d@virginia.edu"}],"points":[{"timestamp":"2023-10-13T23:58:32.468791Z","enrollment_total":0,"class_capacity":30,"wait_tot":0,"wait_cap":0},{"timestamp":"2023-10-19T14:15:23.256471Z","enrollment_total":0,"class_capacity":0,"wait_tot":0,"wait_cap":0},{"timestamp":"2023-11-07T01:14:00.396164Z","enrollment_total":0,"class_capacity":15,"wait_tot":0,"wait_cap":199},{"timestamp":"2023-11-07T02:08:39.072548Z","enrollment_total":3,"class_capacity":15,"wait_tot":0,"wait_cap":199},{"timestamp":"2023-11-08T12:39:21.465681Z","enrollment_total":4,"class_capacity":15,"wait_tot":0,"wait_cap":199},{"timestamp":"2023-11-08T14:38:58.297561Z","enrollment_total":5,"class_capacity":15,"wait_tot":0,"wait_cap":199},{"timestamp":"2023-11-08T15:18:28.477350Z","enrollment_total":6,"class_capacity":15,"wait_tot":0,"wait_cap":199},{"timestamp":"2023-11-08T16:23:04.539371Z","enrollment_total":5,"class_capacity":15,"wait_tot":0,"wait_cap":199},{"timestamp":"2023-11-08T17:15:53.869560Z","enrollment_total":6,"class_capacity":15,"wait_tot":0,"wait_cap":199},{"timestamp":"2023-11-08T19:14:09.876621Z","enrollment_total":7,"class_capacity":15,"wait_tot":0,"wait_cap":199},{"timestamp":"2023-11-28T09:10:02.945253Z","enrollment_total":8,"class_capacity":15,"wait_tot":0,"wait_cap":199},{"timestamp":"2023-11-29T21:08:53.022386Z","enrollment_total":9,"class_capacity":15,"wait_tot":0,"wait_cap":199},{"timestamp":"2024-01-06T23:09:21.917082Z","enrollment_total":8,"class_capacity":15,"wait_tot":0,"wait_cap":199},{"timestamp":"2024-01-09T19:08:11.620605Z","enrollment_total":9,"class_capacity":15,"wait_tot":0,"wait_cap":199},{"timestamp":"2024-01-16T01:53:28.368421Z","enrollment_total":10,"class_capacity":15,"wait_tot":0,"wait_cap":199},{"timestamp":"2024-01-16T21:09:10.368708Z","enrollment_total":11,"class_capacity":15,"wait_tot":0,"wait_cap":199},{"timestamp":"2024-01-16T23:09:29.897101Z","enrollment_total":10,"class_capacity":15,"wait_tot":0,"wait_cap":199},{"timestamp":"2024-01-18T15:10:06.986352Z","enrollment_total":9,"class_capacity":15,"wait_tot":0,"wait_cap":199},{"timestamp":"2024-01-23T18:12:13.403281Z","enrollment_total":8,"class_capacity":15,"wait_tot":0,"wait_cap":199},{"timestamp":"2024-01-25T23:09:34.705375Z","enrollment_total":7,"class_capacity":15,"wait_tot":0,"wait_cap":199}]},"Lecture::002":{"session_key":"Lecture::002","class_nbr":null,"class_section":"002","section_type":"Lecture","topic":"Linguistic Variation in ASL and English","units":"3","instructors":[{"name":"Bruce Sofinski","email":"bs3d@virginia.edu"}],"points":[{"timestamp":"2023-10-13T23:58:32.468791Z","enrollment_total":0,"class_capacity":30,"wait_tot":0,"wait_cap":0},{"timestamp":"2023-10-19T14:15:23.256471Z","enrollment_total":0,"class_capacity":0,"wait_tot":0,"wait_cap":0},{"timestamp":"2023-11-07T01:14:00.396164Z","enrollment_total":0,"class_capacity":15,"wait_tot":0,"wait_cap":199},{"timestamp":"2023-11-07T02:08:39.072548Z","enrollment_total":1,"class_capacity":15,"wait_tot":0,"wait_cap":199},{"timestamp":"2023-11-08T01:12:48.692795Z","enrollment_total":2,"class_capacity":15,"wait_tot":0,"wait_cap":199},{"timestamp":"2023-11-08T16:23:04.539371Z","enrollment_total":3,"class_capacity":15,"wait_tot":0,"wait_cap":199},{"timestamp":"2023-11-08T17:15:53.869560Z","enrollment_total":4,"class_capacity":15,"wait_tot":0,"wait_cap":199},{"timestamp":"2023-11-09T13:20:15.516539Z","enrollment_total":5,"class_capacity":15,"wait_tot":0,"wait_cap":199},{"timestamp":"2023-11-10T19:14:10.988833Z","enrollment_total":6,"class_capacity":15,"wait_tot":0,"wait_cap":199},{"timestamp":"2023-12-06T00:41:28.567589Z","enrollment_total":5,"class_capacity":15,"wait_tot":0,"wait_cap":199},{"timestamp":"2023-12-06T19:08:10.254185Z","enrollment_total":6,"class_capacity":15,"wait_tot":0,"wait_cap":199},{"timestamp":"2023-12-14T18:12:10.724988Z","enrollment_total":7,"class_capacity":15,"wait_tot":0,"wait_cap":199},{"timestamp":"2024-01-08T08:13:16.307986Z","enrollment_total":8,"class_capacity":15,"wait_tot":0,"wait_cap":199},{"timestamp":"2024-01-09T23:09:30.546728Z","enrollment_total":7,"class_capacity":15,"wait_tot":0,"wait_cap":199},{"timestamp":"2024-01-10T22:09:13.513949Z","enrollment_total":8,"class_capacity":15,"wait_tot":0,"wait_cap":199},{"timestamp":"2024-01-12T16:12:06.970077Z","enrollment_total":7,"class_capacity":15,"wait_tot":0,"wait_cap":199},{"timestamp":"2024-01-18T01:52:55.550711Z","enrollment_total":6,"class_capacity":15,"wait_tot":0,"wait_cap":199},{"timestamp":"2024-01-18T21:08:49.797923Z","enrollment_total":7,"class_capacity":15,"wait_tot":0,"wait_cap":199},{"timestamp":"2024-01-23T04:12:03.805959Z","enrollment_total":6,"class_capacity":15,"wait_tot":0,"wait_cap":199}]}}},"ASL::4750":{"subject":"ASL","subject_descr":"American Sign Language","catalog_number":"4750","descr":"Contemporary Deaf Studies","topic":null,"units":"3","sessions":{"Lecture::001":{"session_key":"Lecture::001","class_nbr":null,"class_section":"001","section_type":"Lecture","topic":null,"units":"3","instructors":[{"name":"Christopher Krentz","email":"ck9m@virginia.edu"}],"points":[{"timestamp":"2023-10-13T23:58:32.468791Z","enrollment_total":0,"class_capacity":25,"wait_tot":0,"wait_cap":0},{"timestamp":"2023-11-06T12:34:30.844263Z","enrollment_total":1,"class_capacity":25,"wait_tot":0,"wait_cap":0},{"timestamp":"2023-11-06T14:39:36.393616Z","enrollment_total":2,"class_capacity":25,"wait_tot":0,"wait_cap":0},{"timestamp":"2023-11-06T15:38:54.860895Z","enrollment_total":3,"class_capacity":25,"wait_tot":0,"wait_cap":0},{"timestamp":"2023-11-06T16:23:45.642424Z","enrollment_total":5,"class_capacity":25,"wait_tot":0,"wait_cap":0},{"timestamp":"2023-11-06T16:43:27.913597Z","enrollment_total":6,"class_capacity":25,"wait_tot":0,"wait_cap":0},{"timestamp":"2023-11-06T17:38:48.570786Z","enrollment_total":7,"class_capacity":25,"wait_tot":0,"wait_cap":0},{"timestamp":"2023-11-08T12:39:21.465681Z","enrollment_total":9,"class_capacity":25,"wait_tot":0,"wait_cap":0},{"timestamp":"2023-11-08T16:23:04.539371Z","enrollment_total":10,"class_capacity":25,"wait_tot":0,"wait_cap":0},{"timestamp":"2023-11-08T16:42:11.656552Z","enrollment_total":11,"class_capacity":25,"wait_tot":0,"wait_cap":0},{"timestamp":"2023-11-08T17:15:53.869560Z","enrollment_total":13,"class_capacity":25,"wait_tot":0,"wait_cap":0},{"timestamp":"2023-11-08T18:39:29.892410Z","enrollment_total":15,"class_capacity":25,"wait_tot":0,"wait_cap":0},{"timestamp":"2023-11-08T19:14:09.876621Z","enrollment_total":16,"class_capacity":25,"wait_tot":0,"wait_cap":0},{"timestamp":"2023-11-08T19:38:42.241253Z","enrollment_total":17,"class_capacity":25,"wait_tot":0,"wait_cap":0},{"timestamp":"2023-11-09T12:32:37.622063Z","enrollment_total":19,"class_capacity":25,"wait_tot":0,"wait_cap":0},{"timestamp":"2023-11-09T13:20:15.516539Z","enrollment_total":18,"class_capacity":25,"wait_tot":0,"wait_cap":0},{"timestamp":"2023-11-09T14:38:46.582349Z","enrollment_total":19,"class_capacity":25,"wait_tot":0,"wait_cap":0},{"timestamp":"2023-11-09T15:39:04.467391Z","enrollment_total":20,"class_capacity":25,"wait_tot":0,"wait_cap":0},{"timestamp":"2023-11-09T16:22:48.633140Z","enrollment_total":21,"class_capacity":25,"wait_tot":0,"wait_cap":0},{"timestamp":"2023-11-09T17:15:58.829155Z","enrollment_total":22,"class_capacity":25,"wait_tot":0,"wait_cap":0},{"timestamp":"2023-11-09T20:18:31.350794Z","enrollment_total":21,"class_capacity":25,"wait_tot":0,"wait_cap":0},{"timestamp":"2023-11-10T16:42:01.972637Z","enrollment_total":22,"class_capacity":25,"wait_tot":0,"wait_cap":0},{"timestamp":"2023-11-14T04:20:11.554917Z","enrollment_total":21,"class_capacity":25,"wait_tot":0,"wait_cap":0},{"timestamp":"2023-11-27T17:09:13.492027Z","enrollment_total":22,"class_capacity":25,"wait_tot":0,"wait_cap":0},{"timestamp":"2023-11-30T16:12:19.036651Z","enrollment_total":23,"class_capacity":25,"wait_tot":0,"wait_cap":0},{"timestamp":"2023-12-05T04:11:47.316794Z","enrollment_total":24,"class_capacity":25,"wait_tot":0,"wait_cap":0},{"timestamp":"2023-12-28T22:08:36.846942Z","enrollment_total":25,"class_capacity":25,"wait_tot":0,"wait_cap":0},{"timestamp":"2024-01-16T21:09:10.368708Z","enrollment_total":24,"class_capacity":25,"wait_tot":0,"wait_cap":0},{"timestamp":"2024-01-18T01:52:55.550711Z","enrollment_total":25,"class_capacity":25,"wait_tot":0,"wait_cap":0},{"timestamp":"2024-01-19T00:42:00.422405Z","enrollment_total":24,"class_capacity":25,"wait_tot":0,"wait_cap":0},{"timestamp":"2024-01-19T06:12:50.552714Z","enrollment_total":25,"class_capacity":25,"wait_tot":0,"wait_cap":0},{"timestamp":"2024-01-21T20:09:54.110906Z","enrollment_total":24,"class_capacity":25,"wait_tot":0,"wait_cap":0},{"timestamp":"2024-01-22T20:10:16.620107Z","enrollment_total":23,"class_capacity":25,"wait_tot":0,"wait_cap":0}]}}},"ASL::4993":{"subject":"ASL","subject_descr":"American Sign Language","catalog_number":"4993","descr":"Independent Study in American Sign Language","topic":null,"units":"1 - 3","sessions":{"IND::001":{"session_key":"IND::001","class_nbr":null,"class_section":"001","section_type":"IND","topic":null,"units":"1 - 3","instructors":[{"name":"Gregory Propp","email":"gp5c@virginia.edu"}],"points":[{"timestamp":"2023-10-13T23:58:32.468791Z","enrollment_total":0,"class_capacity":15,"wait_tot":0,"wait_cap":0},{"timestamp":"2024-01-13T19:07:30.534584Z","enrollment_total":1,"class_capacity":15,"wait_tot":0,"wait_cap":0},{"timestamp":"2024-01-31T00:39:16.980396Z","enrollment_total":2,"class_capacity":15,"wait_tot":0,"wait_cap":0}]}}}}}